ez_visual_regression/__init__.py
ez_visual_regression/api.py
ez_visual_regression/cli.py
ez_visual_regression/configuration.py
ez_visual_regression-0.1.0.dist-info/LICENSE
ez_visual_regression-0.1.0.dist-info/METADATA
ez_visual_regression-0.1.0.dist-info/WHEEL
ez_visual_regression-0.1.0.dist-info/entry_points.txt
ez_visual_regression-0.1.0.dist-info/top_level.txt
ez_visual_regression-0.1.0.dist-info/RECORD
