Metadata-Version: 2.1
Name: ez-visual-regression
Version: 0.1.0
Summary: Used to take screenshots with selenium (pages or elements) and compare to baseline
Author: Kieran Wood
Author-email: kieran@canadiancoding.ca
Project-URL: User Docs, https://kieranwood.ca/ez-visual-regression
Project-URL: API Docs, https://ez-visual-regression.readthedocs.io
Project-URL: Source, https://github.com/Descent098/ez-visual-regression
Project-URL: Bug Report, https://github.com/Descent098/ez-visual-regression/issues/new?assignees=Descent098&labels=bug&template=bug_report.md&title=%5BBUG%5D
Project-URL: Feature Request, https://github.com/Descent098/ez-visual-regression/issues/new?labels=enhancement&template=feature_request.md&title=%5BFeature%5D
Project-URL: Roadmap, https://github.com/Descent098/ez-visual-regression/projects
Classifier: Programming Language :: Python :: 3
Classifier: Operating System :: OS Independent
Classifier: Development Status :: 4 - Beta
License-File: LICENSE
Requires-Dist: docopt
Requires-Dist: ez-img-diff
Requires-Dist: selenium
Requires-Dist: webdriver-manager
Requires-Dist: pyyaml
Provides-Extra: ci
Requires-Dist: pytest ; extra == 'ci'
Requires-Dist: pyvirtualdisplay ; extra == 'ci'
Provides-Extra: dev
Requires-Dist: nox ; extra == 'dev'
Requires-Dist: pytest ; extra == 'dev'
Requires-Dist: mkdocs ; extra == 'dev'
Requires-Dist: mkdocs-material ; extra == 'dev'
